setup.py
csssprite/__init__.py
csssprite/csssprite.py
csssprite.egg-info/PKG-INFO
csssprite.egg-info/SOURCES.txt
csssprite.egg-info/dependency_links.txt
csssprite.egg-info/entry_points.txt
csssprite.egg-info/requires.txt
csssprite.egg-info/top_level.txt