Metadata-Version: 1.1
Name: csssprite
Version: 0.9
Summary: A simple class for merging images into a sprite with accompanying css
Home-page: http://github.com/knadh/csssprite
Author: Kailash Nadh
Author-email: kailash.nadh@gmail.com
License: GPL v2
Download-URL: http://github.com/knadh/csssprite
Platform: UNKNOWN
Classifier: Development Status :: 4 - Beta
Classifier: Intended Audience :: Developers
Classifier: Programming Language :: Python
Classifier: Natural Language :: English
Classifier: License :: OSI Approved :: GNU General Public License v2 (GPLv2)
Classifier: Programming Language :: Python :: 2.6
Classifier: Programming Language :: Python :: 2.7
Classifier: Topic :: Software Development :: Libraries :: Python Modules
Classifier: Topic :: Utilities
Classifier: Topic :: Multimedia :: Graphics
Classifier: Topic :: Software Development :: Libraries
